CMakeLists.txt
LICENSE
MANIFEST.in
README.md
pyproject.toml
setup.cfg
setup.py
src/main.cpp
src/trees.c
src/trees.h
src/dpu_program/CMakeLists.txt
src/dpu_program/helloworld.c
src/dpu_program/trivial_checksum_example.c
src/dpu_trees/__init__.py
src/dpu_trees/base_tree.py
src/dpu_trees.egg-info/PKG-INFO
src/dpu_trees.egg-info/SOURCES.txt
src/dpu_trees.egg-info/dependency_links.txt
src/dpu_trees.egg-info/not-zip-safe
src/dpu_trees.egg-info/requires.txt
src/dpu_trees.egg-info/top_level.txt