Metadata-Version: 2.1
Name: dpu-trees
Version: 0.0.3a0
Summary: a package for tree algorithms on DPU
Home-page: https://github.com/SylvanBrocard/dpu_trees
Author: Sylvan Brocard
Author-email: sylvan.brocard@gmail.com
License: MIT
Download-URL: https://github.com/SylvanBrocard/dpu_trees/archive/refs/tags/v0.0.2-alpha.tar.gz
Platform: UNKNOWN
Provides-Extra: test
